assets/upload-cloud.ico
config/linxConfig.EXAMPLE.toml
LICENSE.md
pylinx/__init__.py
pylinx/linx.py
pylinx/linxcore/config.py
pylinx/linxcore/exceptions.py
pylinx/linxcore/utilities.py
pyproject.toml
README.md
cli_pylinx-1.3.1.dist-info/entry_points.txt
cli_pylinx-1.3.1.dist-info/LICENSE.md
cli_pylinx-1.3.1.dist-info/WHEEL
cli_pylinx-1.3.1.dist-info/METADATA
cli_pylinx-1.3.1.dist-info/RECORD
