Metadata-Version: 2.1
Name: cli-pylinx
Version: 1.3.1
Summary: A lightweight CLI for uploading and managing your files on a linx-server instance.
Home-page: https://github.com/DefaultSimon/pylinx
License: MIT
Author: Simon Goričar
Author-email: simon.peter.goricar@gmail.com
Requires-Python: >=3.8,<4.0
Classifier: Development Status :: 4 - Beta
Classifier: Environment :: Console
Classifier: Intended Audience :: Developers
Classifier: License :: OSI Approved :: MIT License
Classifier: Programming Language :: Python :: 3
Classifier: Programming Language :: Python :: 3.8
Classifier: Topic :: Communications :: File Sharing
Requires-Dist: click (>=7.1.2,<8.0.0)
Requires-Dist: click-aliases (>=1.0.1,<2.0.0)
Requires-Dist: colorama (>=0.4.3,<0.5.0)
Requires-Dist: hurry.filesize (>=0.9,<0.10)
Requires-Dist: pyperclip (>=1.8.1,<2.0.0)
Requires-Dist: requests (>=2.24.0,<3.0.0)
Requires-Dist: requests_toolbelt (>=0.9.1,<0.10.0)
Requires-Dist: toml (>=0.10.1,<0.11.0)
Project-URL: Repository, https://github.com/DefaultSimon/pylinx
